bc4py_core.cp37-win_amd64.pyd
bc4py_core-0.1.0.dist-info/METADATA
bc4py_core-0.1.0.dist-info/WHEEL
bc4py_core-0.1.0.dist-info/top_level.txt
bc4py_core-0.1.0.dist-info/RECORD
