Metadata-Version: 2.1
Name: bc4py-core
Version: 0.1.0
Summary: bc4py core library written by Rust
Home-page: https://github.com/namuyan/bc4py_core
License: MIT Licence
Platform: UNKNOWN
Classifier: License :: OSI Approved :: MIT License
Classifier: Programming Language :: Python :: 3
Classifier: Programming Language :: Rust
